eaglec/__init__.py
eaglec/extractMatrix.py
eaglec/predictCore.py
eaglec/searchCandidates.py
eaglec/utilities.py
eaglec/visualize.py
eaglec/data/chm13.gap-mask.10k.pkl
eaglec/data/chm13.gap-mask.500k.pkl
eaglec/data/chm13.gap-mask.50k.pkl
eaglec/data/expected-values.by-res.pkl
eaglec/data/hg19.gap-mask.10k.pkl
eaglec/data/hg19.gap-mask.500k.pkl
eaglec/data/hg19.gap-mask.50k.pkl
eaglec/data/hg38.gap-mask.10k.pkl
eaglec/data/hg38.gap-mask.500k.pkl
eaglec/data/hg38.gap-mask.50k.pkl
eaglec-2.1.1.data/scripts/annotate-gene-fusion
eaglec-2.1.1.data/scripts/evaluateSV
eaglec-2.1.1.data/scripts/filterSV
eaglec-2.1.1.data/scripts/plot-SVbreaks
eaglec-2.1.1.data/scripts/plot-interSVs
eaglec-2.1.1.data/scripts/plot-intraSVs
eaglec-2.1.1.data/scripts/predictSV
eaglec-2.1.1.data/scripts/reformatSV
eaglec-2.1.1.dist-info/LICENSE
eaglec-2.1.1.dist-info/METADATA
eaglec-2.1.1.dist-info/WHEEL
eaglec-2.1.1.dist-info/top_level.txt
eaglec-2.1.1.dist-info/RECORD
