Metadata-Version: 2.1
Name: eaglec
Version: 2.1.1
Summary: Comprehensive detection of multiscale and non-canonical structural variations from Hi-C data
Home-page: https://github.com/XiaoTaoWang/EagleC2
Author: XiaoTao Wang
Author-email: wangxiaotao@fudan.edu.cn
Keywords: Hi-C cooler deep-learning SVs
Classifier: Programming Language :: Python :: 3 :: Only
Classifier: Operating System :: POSIX
Classifier: Development Status :: 3 - Alpha
Classifier: Intended Audience :: Science/Research
Classifier: Topic :: Scientific/Engineering :: Bio-Informatics
License-File: LICENSE
